RandomPi/__init__.py
RandomPi/main.py
RandomPi-2.0.2.dist-info/METADATA
RandomPi-2.0.2.dist-info/WHEEL
RandomPi-2.0.2.dist-info/entry_points.txt
RandomPi-2.0.2.dist-info/top_level.txt
RandomPi-2.0.2.dist-info/RECORD
